{"cameraMode":{"drawMode":0,"name":"Shaded","section":"Shading Mode"},"sceneLighting":true,"audioPlay":false,"sceneViewState":{"showFog":true,"showMaterialUpdate":false,"showSkybox":true,"showFlares":true,"showImageEffects":true,"showParticleSystems":true},"in2DMode":false,"pivot":{"x":0.000030517578125,"y":2.6999969482421877,"z":0.0031239986419677736},"rotation":{"x":-0.11753901839256287,"y":0.038446590304374698,"z":-0.004553219769150019,"w":-0.9923133850097656},"size":16.106433868408204,"orthographic":false}